pyte_prism/__init__.py
pyte_prism-0.0.4.dist-info/LICENSE
pyte_prism-0.0.4.dist-info/WHEEL
pyte_prism-0.0.4.dist-info/METADATA
pyte_prism-0.0.4.dist-info/RECORD
