Metadata-Version: 2.1
Name: pyte-prism
Version: 0.0.4
Summary: A Page Object Model DSL for Python, inspired by Ruby SitePrism
Home-page: https://github.com/fkshom
License: MIT
Author: Shoma FUKUDA
Author-email: fkshom+pypi@gmail.com
Requires-Python: >=3.8,<4.0
Classifier: Development Status :: 3 - Alpha
Classifier: Environment :: Console
Classifier: Intended Audience :: Developers
Classifier: License :: OSI Approved :: MIT License
Classifier: Programming Language :: Python :: 3
Classifier: Programming Language :: Python :: 3.7
Classifier: Programming Language :: Python :: 3.8
Classifier: Topic :: Utilities
Requires-Dist: selenium (>=3.141.0,<4.0.0)
Requires-Dist: uritemplate (>=3.0.1,<4.0.0)
Project-URL: Documentation, https://github.com/fkshom/pyte-prism/wiki
Project-URL: Repository, https://github.com/fkshom/pyte-prism
